{
"type": "FeatureCollection",
"name": "Harta compostarii comunitare Ilfov",
"crs": { "type": "name", "properties": { "name": "urn:ogc:def:crs:OGC:1.3:CRS84" } },
"features": [
{ "type": "Feature", "properties": { "Name": "Stația compostare Grădina SEEDS ", "description": "Grădina SEEDS găzduiește primul punct de compostare comunitară din Măgurele, județul Ilfov. <br><br>Ne găsești pe Strada Turturelelor nr. 48.<br><br>Chat WhatsApp:<br>https:\/\/chat.whatsapp.com\/IIvElP4CqPS7MTJwdTWLQm<br><br>Referentă: Mariana Drăghici", "xcoord": 26.0024052, "ycoord": 44.3598814 }, "geometry": { "type": "Point", "coordinates": [ 26.0024052, 44.3598814, 0.0 ] } }
]
}
